rge/Engine.py
rge/Train.py
rge/__init__.py
rge/utils.py
rge/data/__init__.py
rge/data/chairs2k_group_data.csv
rge/data/filteredCorpus.csv
rge/data/chairs_img_npy/__init__.py
rge/data/chairs_img_npy/chairs2k_group_data.npy
rge/data/chairs_img_npy/numpy/__init__.py
rge/data/chairs_img_npy/numpy/numpy/__init__.py
rge/data/chairs_img_npy/numpy/numpy/images.npy
rge/data/chairs_img_npy/numpy/numpy/names.npy
rge/data/pilot_coll1/__init__.py
rge/data/pilot_coll1/test/__init__.py
rge/data/pilot_coll1/test/msgs.tsv
rge/data/pilot_coll1/test/msgs_concat.tsv
rge/data/pilot_coll1/test/responses.tsv
rge/data/pilot_coll1/test/stims.tsv
rge/data/pilot_coll1/test/vision/__init__.py
rge/data/pilot_coll1/test/vision/dataset.tsv
rge/data/pilot_coll1/train/__init__.py
rge/data/pilot_coll1/train/msgs.tsv
rge/data/pilot_coll1/train/msgs_concat.tsv
rge/data/pilot_coll1/train/responses.tsv
rge/data/pilot_coll1/train/stims.tsv
rge/data/pilot_coll1/train/vision/__init__.py
rge/data/pilot_coll1/train/vision/dataset.tsv
rge/data/pilot_coll1/val/__init__.py
rge/data/pilot_coll1/val/msgs.tsv
rge/data/pilot_coll1/val/msgs_concat.tsv
rge/data/pilot_coll1/val/responses.tsv
rge/data/pilot_coll1/val/stims.tsv
rge/data/pilot_coll1/val/vision/__init__.py
rge/data/pilot_coll1/val/vision/dataset.tsv
rge/datasets/ChairDataset.py
rge/datasets/ColorDataset.py
rge/datasets/CreaturesDataset.py
rge/datasets/__init__.py
rge-1.7.data/scripts/rge
rge-1.7.dist-info/METADATA
rge-1.7.dist-info/WHEEL
rge-1.7.dist-info/top_level.txt
rge-1.7.dist-info/RECORD
