Metadata-Version: 2.1
Name: rge
Version: 1.7
Summary: Engine for Refrence Game Tests
Home-page: https://github.com/cocolab-projects/reference-game-exploration
Author: Ron Arel
Author-email: RonArel123@gmail.com
License: UNKNOWN
Platform: UNKNOWN
Classifier: Programming Language :: Python :: 3
Classifier: License :: OSI Approved :: MIT License
Classifier: Operating System :: OS Independent
